ossai/__init__.py
ossai/decorators/catch_error_dm_user.py
ossai/decorators/to_pdf.py
ossai/handlers.py
ossai/logging_config.py
ossai/slack_context.py
ossai/slack_server.py
ossai/summarizer.py
ossai/topic_analysis.py
ossai/utils.py
open_source_slack_ai-0.7.2.dist-info/LICENSE.md
open_source_slack_ai-0.7.2.dist-info/METADATA
open_source_slack_ai-0.7.2.dist-info/WHEEL
open_source_slack_ai-0.7.2.dist-info/RECORD
