Metadata-Version: 2.3
Name: open-source-slack-ai
Version: 0.7.2
Summary: An open source alternative to some of Slack AI's premium features. Summarize channels and threads any time you want.
Author: Bryce York
Author-email: bryce@bryceyork.com
Requires-Python: >=3.11,<3.12
Classifier: Programming Language :: Python :: 3
Classifier: Programming Language :: Python :: 3.11
Requires-Dist: aiohttp (>=3.8.3,<4.0.0)
Requires-Dist: coverage (>=7.4.4,<8.0.0)
Requires-Dist: fastapi (>=0.111.0,<0.112.0)
Requires-Dist: gensim (>=4.3.2,<5.0.0)
Requires-Dist: langchain (>=0.3.3,<0.4.0)
Requires-Dist: langchain-openai (>=0.2.2,<0.3.0)
Requires-Dist: nltk (>=3.9.1,<4.0.0)
Requires-Dist: openai (>=1.33.0,<2.0.0)
Requires-Dist: python-multipart (>=0.0.9,<0.0.10)
Requires-Dist: reportlab (>=4.2.5,<5.0.0)
Requires-Dist: scikit-learn (>=1.3.0,<2.0.0)
Requires-Dist: scipy (==1.12)
Requires-Dist: slack-bolt (>=1.18.0,<2.0.0)
Requires-Dist: slack-sdk (>=3.21.3,<4.0.0)
Requires-Dist: spacy (>=3.6.1,<4.0.0)
Requires-Dist: uvicorn[standard] (>=0.23.2,<0.24.0)
